<?xml version="1.0" encoding="UTF-8" ?>
<!-- saved from url=(0014)about:internet -->

<tocsection parent="" level="1" id="bookinfo">
 <title>ayuda interplataforma Novell iFolder 3.8.1</title>
 <entry leaf="false" id="overview">Descripción general de iFolder</entry>
 <entry leaf="false" id="accountsprefs">Gestión de cuentas y preferencias de iFolder</entry>
 <entry leaf="false" id="myifolders">Gestión de carpetas iFolder</entry>
 <entry leaf="false" id="coexistmig">Migración y actualización de Novell iFolder</entry>
 <entry leaf="true" id="legal">Información legal</entry>
</tocsection>